icnn/__init__.py
icnn/icnn_dgn_gd.py
icnn/icnn_dgn_lbfgs.py
icnn/icnn_gd.py
icnn/icnn_lbfgs.py
icnn/loss.py
icnn/utils.py
icnn-1.2.2.dist-info/LICENSE
icnn-1.2.2.dist-info/METADATA
icnn-1.2.2.dist-info/WHEEL
icnn-1.2.2.dist-info/top_level.txt
icnn-1.2.2.dist-info/RECORD
