Metadata-Version: 2.1
Name: icnn
Version: 1.2.2
Summary: Deep image reconstruction from CNN features (Inverting CNN)
Home-page: https://github.com/KamitaniLab/icnn
Author: Shen Guo-Hua, Kei Majima
Author-email: brainliner-admin@atr.jp
Maintainer: Shuntaro C. Aoki
Maintainer-email: brainliner-admin@atr.jp
License: MIT
Keywords: neuroscience,brain decoding,deep learning,image reconstruction
Platform: UNKNOWN
Requires-Dist: numpy
Requires-Dist: scipy
